[
    {
        "title": [
            "The Complete Short Stories: Vol. 1"
        ]
    },
    {
        "title": [
            "Nothing Ventured"
        ]
    },
    {
        "title": [
            "Christmas Shopaholic"
        ]
    },
    {
        "title": [
            "Killing Commendatore (Kishidancho Goroshi, #1-2)"
        ]
    },
    {
        "title": [
            "The Complete Short Stories: Vol. 4"
        ]
    },
    {
        "title": [
            "The Complete Short Stories: Vol. 3 [Paperback] Premchand"
        ]
    },
    {
        "title": [
            "The Complete Short Stories: Vol. 2"
        ]
    },
    {
        "title": [
            "Quichotte"
        ]
    },
    {
        "title": [
            "Long Walk to Freedom"
        ]
    },
    {
        "title": [
            "A Legacy of Spies"
        ]
    },
    {
        "title": [
            "The No. 1 Ladies' Detective Agency (No. 1 Ladies' Detective Agency, #1)"
        ]
    },
    {
        "title": [
            "Fire and Blood: A History of the Targaryen Kings from Aegon the Conqueror to Aegon III"
        ]
    },
    {
        "title": [
            "As You Like It"
        ]
    },
    {
        "title": [
            "CHAKRAVYUH - Through the Eyes of the Young Warrior"
        ]
    },
    {
        "title": [
            "The Big Sleep (Philip Marlowe, #1)"
        ]
    },
    {
        "title": [
            "Pride & Prejudice"
        ]
    },
    {
        "title": [
            "HOMER: The Iliad & The Odyssey"
        ]
    },
    {
        "title": [
            "Ulysses"
        ]
    },
    {
        "title": [
            "The Murder of Princess Diana"
        ]
    },
    {
        "title": [
            "The Running Man"
        ]
    },
    {
        "title": [
            "Best of Friends"
        ]
    },
    {
        "title": [
            "Fatal Cure"
        ]
    },
    {
        "title": [
            "The Broker"
        ]
    },
    {
        "title": [
            "The King of Torts"
        ]
    },
    {
        "title": [
            "The Pelican Brief"
        ]
    },
    {
        "title": [
            "A Painted House"
        ]
    },
    {
        "title": [
            "The Chamber"
        ]
    },
    {
        "title": [
            "The Partner"
        ]
    },
    {
        "title": [
            "Beloved"
        ]
    },
    {
        "title": [
            "The Trial"
        ]
    },
    {
        "title": [
            "Brave New World"
        ]
    },
    {
        "title": [
            "21 Lessons for the 21st Century"
        ]
    },
    {
        "title": [
            "To Cut a Long Story Short"
        ]
    },
    {
        "title": [
            "The Reckoning"
        ]
    },
    {
        "title": [
            "The Mahabharata Quest: The Alexander Secret"
        ]
    },
    {
        "title": [
            "The Afghan"
        ]
    },
    {
        "title": [
            "Avenger"
        ]
    },
    {
        "title": [
            "Bloodline"
        ]
    },
    {
        "title": [
            "Murder is Easy (Superintendent Battle #4)"
        ]
    },
    {
        "title": [
            "The Secret of Chimneys"
        ]
    },
    {
        "title": [
            "The Kill List"
        ]
    },
    {
        "title": [
            "Bridge of Clay"
        ]
    },
    {
        "title": [
            "Love Among the Bookshelves"
        ]
    },
    {
        "title": [
            "The Mahabharata Secret"
        ]
    },
    {
        "title": [
            "Son of Bhrigu"
        ]
    },
    {
        "title": [
            "A Hundred Little Flames"
        ]
    },
    {
        "title": [
            "The Palace Of Illusions"
        ]
    },
    {
        "title": [
            "Murder on the Orient Express (Hercule Poirot, #10)"
        ]
    },
    {
        "title": [
            "The Garden of the Finzi Continis"
        ]
    },
    {
        "title": [
            "Circe"
        ]
    },
    {
        "title": [
            "Memoirs of a Geisha"
        ]
    },
    {
        "title": [
            "Don't Tell The Governor"
        ]
    },
    {
        "title": [
            "Lethal White (Cormoran Strike, #4)"
        ]
    },
    {
        "title": [
            "Love A Little Stronger"
        ]
    },
    {
        "title": [
            "Artemis Fowl and the Lost Colony (Artemis Fowl, #5)"
        ]
    },
    {
        "title": [
            "The Maze Runner (Maze Runner, #1)"
        ]
    },
    {
        "title": [
            "Waiting For The Mahatma"
        ]
    },
    {
        "title": [
            "War and Peace"
        ]
    },
    {
        "title": [
            "Crushing It!: How Great Entrepreneurs Build Their Business and Influence\u2014and How You Can, Too"
        ]
    },
    {
        "title": [
            "Think Like a Freak: The Authors of Freakonomics Offer to Retrain Your Brain"
        ]
    },
    {
        "title": [
            "My Grandmother Sends Her Regards and Apologises"
        ]
    },
    {
        "title": [
            "Chanakya (Itihasa Series)"
        ]
    },
    {
        "title": [
            "All the Light We Cannot See"
        ]
    },
    {
        "title": [
            "Everyone Has a Story 2"
        ]
    },
    {
        "title": [
            "The Old Man and His God: Discovering the Spirit of India"
        ]
    },
    {
        "title": [
            "Molecules of Emotion: The Science Behind Mind-Body Medicine"
        ]
    },
    {
        "title": [
            "The Leader who had no Title: A Modern Fable on Real Success in Business & in Life"
        ]
    },
    {
        "title": [
            "Midnight at the Bright Ideas Bookstore"
        ]
    },
    {
        "title": [
            "Britt-Marie Was Here"
        ]
    },
    {
        "title": [
            "Corporate Chanakya"
        ]
    },
    {
        "title": [
            "Roots"
        ]
    },
    {
        "title": [
            "Seventeen"
        ]
    },
    {
        "title": [
            "A Fine Balance"
        ]
    },
    {
        "title": [
            "I Am Krishna"
        ]
    },
    {
        "title": [
            "The Wise Man's Fear (The Kingkiller Chronicle, #2)"
        ]
    },
    {
        "title": [
            "Rage of Angels"
        ]
    },
    {
        "title": [
            "Khullam Khulla: Rishi Kapoor Uncensored"
        ]
    },
    {
        "title": [
            "The Discovery of India"
        ]
    },
    {
        "title": [
            "American Gods"
        ]
    },
    {
        "title": [
            "Brida"
        ]
    },
    {
        "title": [
            "A Clash of Kings (A Song of Ice and Fire, #2)"
        ]
    },
    {
        "title": [
            "A Song of Ice and Fire, 7 Volumes (A Song of Ice and Fire, #1-5)"
        ]
    },
    {
        "title": [
            "The Case of the Curious Bride"
        ]
    },
    {
        "title": [
            "The Case of the Lucky Legs (A Perry Mason Mystery, #3)"
        ]
    },
    {
        "title": [
            "The Case of the Counterfeit Eye (A Perry Mason Mystery, #6)"
        ]
    },
    {
        "title": [
            "The Case of the Howling Dog (A Perry Mason Mystery, #4)"
        ]
    },
    {
        "title": [
            "Unfinished Portrait"
        ]
    },
    {
        "title": [
            "And Then There Were None"
        ]
    },
    {
        "title": [
            "Murder on the Orient Express"
        ]
    },
    {
        "title": [
            "The Reptile Room (A Series of Unfortunate Events, #2)"
        ]
    },
    {
        "title": [
            "The Wide Window"
        ]
    },
    {
        "title": [
            "The Austere Academy"
        ]
    },
    {
        "title": [
            "The Miserable Mill (A Series of Unfortunate Events, #4)"
        ]
    },
    {
        "title": [
            "The Ersatz Elevator"
        ]
    },
    {
        "title": [
            "The Vile Village (A Series of Unfortunate Events, #7)"
        ]
    },
    {
        "title": [
            "The Hostile Hospital (A Series of Unfortunate Events, #8)"
        ]
    },
    {
        "title": [
            "The Carnivorous Carnival"
        ]
    },
    {
        "title": [
            "The Penultimate Peril (A Series of Unfortunate Events #12)"
        ]
    },
    {
        "title": [
            "The End (A Series Of Unfortunate Events #13)"
        ]
    },
    {
        "title": [
            "The Slippery Slope (A Series of Unfortunate Events, #10)"
        ]
    },
    {
        "title": [
            "The Grim Grotto (A Series Of Unfortunate Events #11)"
        ]
    },
    {
        "title": [
            "The Bad Beginning (A Series of Unfortunate Events, #1)"
        ]
    },
    {
        "title": [
            "Best Served Cold (First Law World, #4)"
        ]
    },
    {
        "title": [
            "Before They Are Hanged (The First Law, #2)"
        ]
    },
    {
        "title": [
            "The Blade Itself (The First Law, #1)"
        ]
    },
    {
        "title": [
            "Last Argument of Kings (The First Law, #3)"
        ]
    },
    {
        "title": [
            "The Heroes (First Law World, #5)"
        ]
    },
    {
        "title": [
            "The Perks of Being a Wallflower"
        ]
    },
    {
        "title": [
            "Heads You Win"
        ]
    },
    {
        "title": [
            "It"
        ]
    },
    {
        "title": [
            "The Fox"
        ]
    },
    {
        "title": [
            "The Guest of Honor"
        ]
    },
    {
        "title": [
            "David Copperfield"
        ]
    },
    {
        "title": [
            "The Enchantress of Florence"
        ]
    },
    {
        "title": [
            "Power of the Plus Factor"
        ]
    },
    {
        "title": [
            "Jackdaws"
        ]
    },
    {
        "title": [
            "What Color Is Your Parachute? 2009: A Practical Manual for Job-Hunters and Career-Changers"
        ]
    },
    {
        "title": [
            "The Magic (The Secret, #1)"
        ]
    },
    {
        "title": [
            "New Moon (Twilight, #2)"
        ]
    },
    {
        "title": [
            "A Prison Diary"
        ]
    },
    {
        "title": [
            "False Impression"
        ]
    },
    {
        "title": [
            "Prisoner Of Birth"
        ]
    },
    {
        "title": [
            "The Bourne Sanction (Jason Bourne, #6)"
        ]
    },
    {
        "title": [
            "The Namesake"
        ]
    },
    {
        "title": [
            "Nothing to Lose (Jack Reacher, #12)"
        ]
    },
    {
        "title": [
            "Mahasamara -4 Dharma"
        ]
    },
    {
        "title": [
            "\u0915\u0930\u094d\u092e - Mahasamar-3"
        ]
    },
    {
        "title": [
            "Peril at End House"
        ]
    },
    {
        "title": [
            "The Shining"
        ]
    },
    {
        "title": [
            "Origin (Robert Langdon, #5)"
        ]
    },
    {
        "title": [
            "A Quiver Full of Arrows"
        ]
    },
    {
        "title": [
            "The Rooster Bar"
        ]
    },
    {
        "title": [
            "As the Crow Flies"
        ]
    },
    {
        "title": [
            "Calico Joe"
        ]
    },
    {
        "title": [
            "Sidney Sheldon's Mistress of the Game"
        ]
    },
    {
        "title": [
            "Sidney Sheldon's The Tides of Memory"
        ]
    },
    {
        "title": [
            "WINDMILLS OF THE GODS"
        ]
    },
    {
        "title": [
            "Mossad: The Greatest Missions of the Israeli Secret"
        ]
    },
    {
        "title": [
            "The Goldfinch"
        ]
    },
    {
        "title": [
            "Schindler's List"
        ]
    },
    {
        "title": [
            "The Nightingale"
        ]
    },
    {
        "title": [
            "The Boy in the Striped Pyjamas"
        ]
    },
    {
        "title": [
            "The Underground Railroad"
        ]
    },
    {
        "title": [
            "The Paris Wife"
        ]
    },
    {
        "title": [
            "It Happened That Night: A Tale Of Love, Deceit And Murder"
        ]
    },
    {
        "title": [
            "Mistress of the Throne"
        ]
    },
    {
        "title": [
            "The Tattooist of Auschwitz"
        ]
    },
    {
        "title": [
            "Go Set a Watchman"
        ]
    },
    {
        "title": [
            "The Girl in Room 105"
        ]
    },
    {
        "title": [
            "Lincoln in the Bardo"
        ]
    },
    {
        "title": [
            "Eleanor Oliphant Is Completely Fine"
        ]
    },
    {
        "title": [
            "Beartown (Beartown, #1)"
        ]
    },
    {
        "title": [
            "I Am Malala"
        ]
    },
    {
        "title": [
            "Think and Grow Rich"
        ]
    },
    {
        "title": [
            "The Final Diagnosis"
        ]
    },
    {
        "title": [
            "Don Quixote"
        ]
    },
    {
        "title": [
            "Persepolis: The Story of a Childhood and The Story of a Return"
        ]
    },
    {
        "title": [
            "I Am the Messenger"
        ]
    },
    {
        "title": [
            "Three Thousand Stitches: Ordinary People, Extraordinary Lives"
        ]
    },
    {
        "title": [
            "Homo Deus: A Brief History of Tomorrow"
        ]
    },
    {
        "title": [
            "Chicken Soup for the Golden Soul"
        ]
    },
    {
        "title": [
            "Chicken Soup for the Teenage Soul III"
        ]
    },
    {
        "title": [
            "Chicken Soup for the Teenage Soul on Love and Friendship"
        ]
    },
    {
        "title": [
            "Chicken Soup for the Teenage Soul"
        ]
    },
    {
        "title": [
            "Chicken Soup For The Soul: Dads & Daughters"
        ]
    },
    {
        "title": [
            "Chicken Soup for the Soul: 101 Stories to Open the Heart and Rekindle the Spirit"
        ]
    },
    {
        "title": [
            "Uzumaki: The Art of Naruto"
        ]
    },
    {
        "title": [
            "An Autobiography: The Story of My Experiments with Truth"
        ]
    },
    {
        "title": [
            "An Autobiography or the Story of My Experiments with Truth"
        ]
    },
    {
        "title": [
            "Dongri To Dubai : Six Decades of The Mumbai Mafia"
        ]
    },
    {
        "title": [
            "I Inspire: A Unique Treasure Hunt"
        ]
    },
    {
        "title": [
            "Road to Success: Timeless Advice for Today"
        ]
    },
    {
        "title": [
            "How to live on 24 hours a day"
        ]
    },
    {
        "title": [
            "Life Lessons for Busy Moms"
        ]
    },
    {
        "title": [
            "Inspiration: Your Ultimate Calling"
        ]
    },
    {
        "title": [
            "The One Thing: The Surprisingly Simple Truth Behind Extraordinary Results"
        ]
    },
    {
        "title": [
            "Who Moved My Interest Rate?: Leading the Reserve Bank of India Through Five Turbulent Years"
        ]
    },
    {
        "title": [
            "Chanakya in Daily Life"
        ]
    },
    {
        "title": [
            "Homeopathy: Every Man's Guide to Homeopathy"
        ]
    },
    {
        "title": [
            "When Trying to Change Him Is Hurting You: Nine Secrets Every Woman Should Know"
        ]
    },
    {
        "title": [
            "The Theory of Everything: The Origin and Fate of the Universe"
        ]
    },
    {
        "title": [
            "A Brief History Of Time: From the Big Bang To Black Holes"
        ]
    },
    {
        "title": [
            "Life Simplified!"
        ]
    },
    {
        "title": [
            "How to Overcome Mental Tension"
        ]
    },
    {
        "title": [
            "The Art Of War"
        ]
    },
    {
        "title": [
            "10 Secrets For Success And Inner Peace"
        ]
    },
    {
        "title": [
            "Indian Superfoods"
        ]
    },
    {
        "title": [
            "Ace against Odds"
        ]
    },
    {
        "title": [
            "The Success Factor: Master the Secret of a Winning Mindset"
        ]
    },
    {
        "title": [
            "Philosophy: All That Matters"
        ]
    },
    {
        "title": [
            "Einstein: The Life And Times"
        ]
    },
    {
        "title": [
            "The Definitive Spa and Body Therapist's Handbook: The 5 Keys to Unlimited Energy, Balance and Bliss"
        ]
    },
    {
        "title": [
            "Symbiosis: Biography Of An Idea"
        ]
    },
    {
        "title": [
            "AB: The Autobiography"
        ]
    },
    {
        "title": [
            "Mein Kampf"
        ]
    },
    {
        "title": [
            "My Life: An Illustrated Biography"
        ]
    },
    {
        "title": [
            "The Intelligent Investor"
        ]
    },
    {
        "title": [
            "Working with Emotional Intelligence"
        ]
    },
    {
        "title": [
            "Aristotle Life and Works"
        ]
    },
    {
        "title": [
            "Zero to One: Notes on Start Ups, or How to Build the Future"
        ]
    }
]